asyncapi/__init__.py
asyncapi/api.py
asyncapi/builder.py
asyncapi/docs.py
asyncapi/docs_filters.py
asyncapi/exceptions.py
asyncapi/py.typed
asyncapi/schema.py
asyncapi/specification_v2_0_0.py
asyncapi/subscriber.py
asyncapi/docs-template/.all-contributorsrc
asyncapi/docs-template/.gitignore
asyncapi/docs-template/README.md
asyncapi/docs-template/.github/workflows/automerge-release-pr-bump.yml
asyncapi/docs-template/.github/workflows/pull-request-testing.yml
asyncapi/docs-template/.github/workflows/release.yml
asyncapi/docs-template/.github/workflows/stale-issues-prs.yml
asyncapi/docs-template/.github/workflows/welcome-first-time-contrib.yml
asyncapi/docs-template/partials/content.html
asyncapi/docs-template/partials/example.html
asyncapi/docs-template/partials/introduction.html
asyncapi/docs-template/partials/message.html
asyncapi/docs-template/partials/messages.html
asyncapi/docs-template/partials/operation.html
asyncapi/docs-template/partials/operations.html
asyncapi/docs-template/partials/schema-prop.html
asyncapi/docs-template/partials/schema.html
asyncapi/docs-template/partials/servers.html
asyncapi/docs-template/partials/sidebar.html
asyncapi/docs-template/partials/sliced-string.html
asyncapi/docs-template/partials/tags.html
asyncapi/docs-template/partials/type.html
asyncapi/docs-template/template/index.html
asyncapi/docs-template/template/css/atom-one-dark.min.css
asyncapi/docs-template/template/css/main.css
asyncapi/docs-template/template/css/tailwind.min.css
asyncapi/docs-template/template/js/highlight.min.js
asyncapi/docs-template/template/js/main.js
asyncapi/events/__init__.py
asyncapi/events/handler.py
asyncapi/events/backends/__init__.py
asyncapi/events/backends/gcloud_pubsub.py
asyncapi/events/backends/kafka.py
asyncapi-0.14.1.dist-info/entry_points.txt
asyncapi-0.14.1.dist-info/LICENSE
asyncapi-0.14.1.dist-info/WHEEL
asyncapi-0.14.1.dist-info/METADATA
asyncapi-0.14.1.dist-info/RECORD
