Metadata-Version: 2.1
Name: asyncapi
Version: 0.14.1
Summary: asyncapi
Home-page: https://github.com/dutradda/asyncapi
License: UNKNOWN
Author: Diogo Dutra
Author-email: diogodutradamata@gmail.com
Requires-Python: >=3.8
Classifier: License :: OSI Approved :: MIT License
Classifier: Intended Audience :: Developers
Classifier: Programming Language :: Python :: 3.8
Classifier: Programming Language :: Python :: 3 :: Only
Classifier: Topic :: Database
Requires-Dist: broadcaster
Requires-Dist: jsondaora
Requires-Dist: mkdocs ; extra == "dev-doc"
Requires-Dist: mkdocs-material ; extra == "dev-doc"
Requires-Dist: markdown-include ; extra == "dev-doc"
Requires-Dist: apidaora ; extra == "docs"
Requires-Dist: jinja2 ; extra == "docs"
Requires-Dist: markdown ; extra == "docs"
Requires-Dist: uvicorn ; extra == "docs"
Requires-Dist: google-cloud-pubsub>=1,<2 ; extra == "gcloud-pubsub"
Requires-Dist: requests ; extra == "http"
Requires-Dist: aiokafka ; extra == "kafka"
Requires-Dist: asyncpg ; extra == "postgres"
Requires-Dist: asyncio-redis ; extra == "redis"
Requires-Dist: typer ; extra == "subscriber"
Requires-Dist: black ; extra == "test"
Requires-Dist: isort ; extra == "test"
Requires-Dist: ipython ; extra == "test"
Requires-Dist: mypy ; extra == "test"
Requires-Dist: pytest-asyncio ; extra == "test"
Requires-Dist: pytest-cov ; extra == "test"
Requires-Dist: pytest-mock ; extra == "test"
Requires-Dist: pytest ; extra == "test"
Requires-Dist: flake8 ; extra == "test"
Requires-Dist: bumpversion ; extra == "test"
Requires-Dist: jsondaora ; extra == "test"
Requires-Dist: asynctest ; extra == "test"
Requires-Dist: pyyaml ; extra == "yaml"
Project-URL: Documentation, https://dutradda.github.io/asyncapi/
Provides-Extra: dev-doc
Provides-Extra: docs
Provides-Extra: gcloud-pubsub
Provides-Extra: http
Provides-Extra: kafka
Provides-Extra: postgres
Provides-Extra: redis
Provides-Extra: subscriber
Provides-Extra: test
Provides-Extra: yaml
